{
  "TypeRacer": {
    "value": {
      "266063988209483790": {
        "wins": 21,
        "record": [
          11.733,
          76.417,
          135.664,
          194.579,
          11.742,
          10.05,
          3.46,
          6.886,
          5.078,
          2.498,
          10.702,
          13.931,
          35.943,
          27.242,
          13.769,
          29.287,
          40.937,
          42.735,
          15.297,
          77.344,
          58.884
        ]
      },
      "647344650201464832": {
        "wins": 0,
        "record": []
      }
    }
  }
}